sort_algorithms_pack/__init__.py
sort_algorithms_pack/sort.py
sort_algorithms_pack-0.4.dist-info/licenses/LICENSE
sort_algorithms_pack-0.4.dist-info/METADATA
sort_algorithms_pack-0.4.dist-info/WHEEL
sort_algorithms_pack-0.4.dist-info/top_level.txt
sort_algorithms_pack-0.4.dist-info/RECORD
