Metadata-Version: 2.4
Name: sort-algorithms-pack
Version: 0.4
Summary: Consists  of sorting algorithms(Merge Sort,Quick Sort,Insertion Sort ,Bubble sortS)
Author: Arpit Kumar
Author-email: arpitkumar172004@gmail.com
License-File: LICENSE
Dynamic: author
Dynamic: author-email
Dynamic: license-file
Dynamic: summary
